CHANGELOG.rst
django_guid/__init__.py
django_guid/api.py
django_guid/apps.py
django_guid/config.py
django_guid/context.py
django_guid/integrations/__init__.py
django_guid/integrations/base.py
django_guid/integrations/celery/__init__.py
django_guid/integrations/celery/config.py
django_guid/integrations/celery/context.py
django_guid/integrations/celery/integration.py
django_guid/integrations/celery/log_filters.py
django_guid/integrations/celery/logging.py
django_guid/integrations/celery/signals.py
django_guid/integrations/sentry.py
django_guid/log_filters.py
django_guid/middleware.py
django_guid/py.typed
django_guid/signals.py
django_guid/utils.py
django_riso_guid-3.4.0.dist-info/LICENSE
django_riso_guid-3.4.0.dist-info/METADATA
django_riso_guid-3.4.0.dist-info/WHEEL
django_riso_guid-3.4.0.dist-info/RECORD
